{
  "id": "TRD",
  "name": "Trade in goods",
  "description_short": "Monthly statistics on euro area trade in goods, covering exports and imports by product category and partner country. The key source for merchandise trade analysis in the euro area.",
  "concepts": [
    "trade in goods",
    "merchandise trade",
    "exports",
    "imports",
    "trade balance",
    "goods trade",
    "bilateral trade",
    "product breakdown",
    "SITC",
    "intra-EU trade",
    "extra-EU trade",
    "terms of trade",
    "trade volumes",
    "unit values"
  ],
  "use_cases": [
    "What is the euro area trade balance in goods with the United States?",
    "How have export volumes evolved compared to export values?",
    "Which product categories are driving euro area export growth?",
    "How does intra-EU trade compare to extra-EU trade in magnitude?"
  ],
  "primary_frequency": "M",
  "geographic_coverage": "euro_area_and_countries",
  "key_dimensions": [
    "TRD_FLOW",
    "TRD_PRODUCT",
    "COUNT_AREA",
    "TRD_SUFFIX",
    "ADJUSTMENT"
  ],
  "enriched_at": "2026-03-18T00:00:00Z"
}